{
  "paper": {
    "schema_version": "1.0",
    "canonical_key": "arxiv:2512.19806",
    "arxiv_id": "2512.19806",
    "arxiv_version": 2,
    "inspire_id": null,
    "doi": null,
    "title_en": "Local Operations and Field Mediated Entanglement without a Local Tensor Product Structure",
    "abstract_en": "Quantum information has become a powerful tool for probing the structure of quantum field theories, yet its application to gauge theories remains subtle. On the one hand, quantum information theory assumes subsystem locality, i.e.~the factorization of the total Hilbert space into subsystems. On the other hand, gauge constraints prevent the total Hilbert space to decompose into a spacetime-local tensor product structure. Because the Hilbert space structure of gauge theories does not accommodate the subsystem decomposition used in quantum information theory, standard information-theoretic results, such as the Local Operations and Classical Communication (LOCC) theorem, cannot be used straightforwardly in the context of gauge theories. In this work, we bridge this gap in the case of a two-dimensional lattice gauge model that captures key features of electromagnetism. In particular, we construct gauge-invariant local algebras and derive a physically meaningful decomposition of the Hilbert space, providing an operationally consistent notion of locality in the absence of a local tensor-product structure. We apply this framework to field-mediated entanglement protocols relevant to proposed tests of the quantum nature of gravity. We show that the discretized version of electromagnetism satisfies an analogue of the LOCC theorem: entanglement cannot be generated without genuine quantum field interactions, even in the absence of a spacetime-local tensor product factorization of the Hilbert space. This may point towards an operational way to define a subsystem structure for gauge theories.",
    "authors": [
      "Alberto Spalvieri",
      "Sébastien Christophe Garmier",
      "Flaminia Giacomini"
    ],
    "categories": [
      "quant-ph",
      "gr-qc"
    ],
    "submitted_at": "2025-12-22T19:02:14Z",
    "updated_at": "2026-07-06T13:28:57Z",
    "document_types": [],
    "journal_ref": null,
    "publication_info": [],
    "citation_count": null,
    "citation_count_without_self_citations": null,
    "abs_url": "https://arxiv.org/abs/2512.19806v2",
    "pdf_url": "https://arxiv.org/pdf/2512.19806v2",
    "inspire_url": null,
    "is_update": true,
    "source_provenance": [
      {
        "source": "arxiv",
        "record_id": "2512.19806",
        "fetched_at": "2026-07-13T12:53:32.407803Z",
        "url": "https://arxiv.org/abs/2512.19806v2"
      }
    ],
    "is_demo": false
  },
  "filter_result": {
    "schema_version": "1.0",
    "passed": false,
    "candidate_topics": [],
    "high_weight_hits": [],
    "medium_weight_hits": [],
    "negative_hits": [],
    "reasons": [
      "未达到主题关键词门槛"
    ],
    "deterministic_score": 0
  },
  "schema_version": "1.0"
}