{
  "paper": {
    "schema_version": "1.0",
    "canonical_key": "arxiv:2607.14384",
    "arxiv_id": "2607.14384",
    "arxiv_version": null,
    "inspire_id": "3181124",
    "doi": null,
    "title_en": "Circuit complexity lower bounds for quantum spin glasses",
    "abstract_en": "A central question in quantum information theory is the circuit complexity of states arising from standard many-body models. We study this question for quantum $p$-spin glasses, random Hamiltonians whose interactions act on $p$-tuples of qubits through Pauli strings. Anschuetz, Gamarnik, and Kiani (arXiv:2404.07231) showed that the optimum energy is separated from the best energy achievable by product states. This leaves open whether shallow circuits can close the gap, since even depth-one circuits can generate entanglement. We show that the entanglement needed to close the product-state gap cannot be generated at shallow depth. When the average interaction degree grows with $n$, we prove that, for all sufficiently large fixed $p$, any circuit preparing an $n$-qubit state whose normalized energy is within a fixed positive constant of the optimum must have depth $Ω_p(\\log n)$. In the bounded-average-degree regime, we prove a fixed-depth obstruction: for every fixed $D$, a sufficiently large degree prefactor rules out depth-$D$ preparation of near-ground states. Both results hold uniformly over circuits with an arbitrary number of ancilla qubits. Our results give an obstruction in the spirit of the No Low-Energy Trivial States problem of Freedman and Hastings (arXiv:1301.1363), but for random quantum spin glasses rather than code-based Hamiltonians such as those of Anshu, Breuckmann, and Nirkhe (arXiv:2206.13228), whose ground states admit polynomial-size preparation circuits. This setting opens a probabilistic route to NLTS-like questions: we recast state-preparation lower bounds for random quantum Hamiltonians as uniform control of Gaussian processes indexed by shallow circuits.",
    "authors": [
      "Al-Ghattas, Omar",
      "Gamarnik, David"
    ],
    "categories": [],
    "submitted_at": "2026-07-15T00:00:00Z",
    "updated_at": "2026-07-18T04:09:41.613857Z",
    "document_types": [
      "article"
    ],
    "journal_ref": null,
    "publication_info": [],
    "citation_count": 0,
    "citation_count_without_self_citations": 0,
    "abs_url": null,
    "pdf_url": null,
    "inspire_url": "https://inspirehep.net/literature/3181124",
    "is_update": false,
    "source_provenance": [
      {
        "source": "inspire",
        "record_id": "3181124",
        "fetched_at": "2026-07-21T00:16:08.085426Z",
        "url": "https://inspirehep.net/literature/3181124"
      }
    ],
    "is_demo": false
  },
  "filter_result": {
    "schema_version": "1.0",
    "passed": false,
    "candidate_topics": [],
    "high_weight_hits": [],
    "medium_weight_hits": [],
    "negative_hits": [],
    "reasons": [
      "未达到主题关键词门槛"
    ],
    "deterministic_score": 0
  },
  "schema_version": "1.0"
}