{
  "paper": {
    "schema_version": "1.0",
    "canonical_key": "arxiv:2607.16774",
    "arxiv_id": "2607.16774",
    "arxiv_version": 1,
    "inspire_id": "3181768",
    "doi": null,
    "title_en": "Quantum phases at high chemical potential in 2-flavor matrix-QC$_2$D",
    "abstract_en": "We investigate the matrix model of two-color two-flavor QCD (matrix-QCD$_{2,2}$) in regimes with large baryon ($μ_{_B}$), isospin ($μ_{_I}$), and/or chiral ($c$) chemical potentials. In these regimes, the Hamiltonian simplifies considerably, making it possible to investigate the ground state for intermediate and strong Yang-Mills coupling. By diagonalizing the Hamiltonian using the variational techniques, we show that in regimes where $μ_{_B}$ and $c$ (or $μ_{_B}$ and $μ_{_I}$) dominate, tuning the remaining parameters leads to quantum phase transitions (QPTs). These transitions form a complex web of phases, each of which has a ground state uniquely labelled by baryon number $B$ and isospin $I$. Several of these phases are LOFF-like, characterized by a ground state carrying non-zero spin and hence spontaneously breaking rotational symmetry. These results are consistent with older effective field theory predictions by Splittorff-Son-Stephanov \\cite{Splittorff:2000mm}. The fermionic content of these LOFF-like ground states consists of spin-1 di-(anti-) quarks which are analogous to Cooper pairs. We compute the spin-fraction carried by the quarks and find that it constitutes a significant portion -- in some cases nearly the entirety -- of the total spin.",
    "authors": [
      "Nirmalendu Acharyya",
      "Prasanjit Aich",
      "Arkajyoti Bandyopadhyay",
      "Sachindeo Vaidya"
    ],
    "categories": [
      "hep-th",
      "hep-lat"
    ],
    "submitted_at": "2026-07-18T00:00:00Z",
    "updated_at": "2026-07-21T04:08:07.408093Z",
    "document_types": [
      "article"
    ],
    "journal_ref": null,
    "publication_info": [],
    "citation_count": 0,
    "citation_count_without_self_citations": 0,
    "abs_url": "https://arxiv.org/abs/2607.16774v1",
    "pdf_url": "https://arxiv.org/pdf/2607.16774v1",
    "inspire_url": "https://inspirehep.net/literature/3181768",
    "is_update": false,
    "source_provenance": [
      {
        "source": "arxiv",
        "record_id": "2607.16774",
        "fetched_at": "2026-07-22T00:12:31.971466Z",
        "url": "https://arxiv.org/abs/2607.16774v1"
      },
      {
        "source": "inspire",
        "record_id": "3181768",
        "fetched_at": "2026-07-22T00:12:31.971466Z",
        "url": "https://inspirehep.net/literature/3181768"
      }
    ],
    "is_demo": false
  },
  "filter_result": {
    "schema_version": "1.0",
    "passed": false,
    "candidate_topics": [],
    "high_weight_hits": [],
    "medium_weight_hits": [],
    "negative_hits": [],
    "reasons": [
      "未达到主题关键词门槛"
    ],
    "deterministic_score": 0
  },
  "schema_version": "1.0"
}