{
  "paper": {
    "schema_version": "1.0",
    "canonical_key": "arxiv:2607.10658",
    "arxiv_id": "2607.10658",
    "arxiv_version": 1,
    "inspire_id": "3179977",
    "doi": null,
    "title_en": "Polarization-dependent observational signatures of Weyl-coupled photons around a black hole",
    "abstract_en": "A photon coupled non-minimally to the Weyl tensor propagates differently in its two linear polarization states: the vacuum around a black hole becomes a birefringent medium. On a Schwarzschild background the coupling $α$ splits the photon sphere and the critical impact parameter of the two polarizations, producing a double shadow and a polarization-dependent photon ring; the two shadow edges separate by $62\\%$ of the shadow radius at $α/M^2=0.75$. We compute a unified set of wave-optical and geometric-optical observables for both polarizations across a range of $α$: greybody factors, absorption cross sections, differential cross sections and their glories, a backward birefringence signal, shadows, photon rings, and null trajectories. The two-polarization scattering matrices are extracted with a Riccati--Hankel matching scheme that keeps the phase-sensitive observables reliable, and the geometric-optics chain is cross-validated with three independent ray tracers. The cleanest diagnostic is the backward signal: it is protected by parity and vanishes identically at $α=0$.",
    "authors": [
      "Mao-Yuan Wan",
      "Chen Wu"
    ],
    "categories": [
      "gr-qc",
      "hep-th"
    ],
    "submitted_at": "2026-07-12T00:00:00Z",
    "updated_at": "2026-07-15T04:13:11.116111Z",
    "document_types": [
      "article"
    ],
    "journal_ref": null,
    "publication_info": [],
    "citation_count": 0,
    "citation_count_without_self_citations": 0,
    "abs_url": "https://arxiv.org/abs/2607.10658v1",
    "pdf_url": "https://arxiv.org/pdf/2607.10658v1",
    "inspire_url": "https://inspirehep.net/literature/3179977",
    "is_update": false,
    "source_provenance": [
      {
        "source": "arxiv",
        "record_id": "2607.10658",
        "fetched_at": "2026-07-16T00:14:49.985540Z",
        "url": "https://arxiv.org/abs/2607.10658v1"
      },
      {
        "source": "inspire",
        "record_id": "3179977",
        "fetched_at": "2026-07-16T00:14:49.985540Z",
        "url": "https://inspirehep.net/literature/3179977"
      }
    ],
    "is_demo": false
  },
  "filter_result": {
    "schema_version": "1.0",
    "passed": false,
    "candidate_topics": [],
    "high_weight_hits": [],
    "medium_weight_hits": [],
    "negative_hits": [],
    "reasons": [
      "未达到主题关键词门槛"
    ],
    "deterministic_score": 0
  },
  "schema_version": "1.0"
}