{
  "paper": {
    "schema_version": "1.0",
    "canonical_key": "arxiv:2607.15921",
    "arxiv_id": "2607.15921",
    "arxiv_version": 1,
    "inspire_id": "3181663",
    "doi": null,
    "title_en": "Relativistic Scaling and Magnetization-Current Feedback in Stern Gerlach-Modified Pair-Plasma Reconnection: SpinPIC2D Validation and Nonlinear Regimes",
    "abstract_en": "We investigate the relativistic scaling and electromagnetic feedback of Stern--Gerlach (SG) force driven spin transport in pair-plasma reconnection with SpinPIC2D. The model advances relativistic proper momentum and magnetic BMT spin precession, applies the SG force, deposits spin magnetization, and includes $\\mathbf J_M=\\nabla\\times\\mathbf M$ in Ampere's law. In a weak-seed scan at fixed $γ_{\\rm tr}=2$, the normalized global magnetic flux-growth remains near the classical control-run for $Ξ\\le0.1$, is $0.016$ at $Ξ=0.4$, and reaches approximately $0.12$ and $0.25$ at $Ξ=0.7$ and 1, respectively over $3\\le t/τ_{\\rm sp}\\le7$. Because $\\partial/\\partial y=0$ in the 2.5-D geometry, the direct $y$-directed SG term vanishes and the enhancement is indirect: sheet-normal SG sorting restructures branch-resolved electron and positron velocity distributions which results in changes in pressure moments and generates a layered magnetization current. Along a fixed-$χ_{\\rm sim}$ family, increasing $γ_{\\rm tr}$ reduces $Ξ$ and suppresses branch sorting, whereas the matched-control flux-growth enhancement remains positive for $γ_{\\rm tr}=2,3,5$. Retuning $χ_{\\rm sim}$ to hold $Ξ=1$ does not preserve nonlinear similarity: both the coupling and $J_{M,y}$ increase with $γ_{\\rm tr}$, and the $γ_{\\rm tr}=5$ case develops a multi-X-line state. Thus $Ξ$ orders the onset of SG-modified reconnection, while the nonlinear response also depends on the absolute spin coupling and magnetization-current amplitude.",
    "authors": [
      "K. Nykyri"
    ],
    "categories": [
      "physics.plasm-ph",
      "astro-ph.HE"
    ],
    "submitted_at": "2026-07-17T00:00:00Z",
    "updated_at": "2026-07-21T04:17:24.674462Z",
    "document_types": [
      "article"
    ],
    "journal_ref": null,
    "publication_info": [],
    "citation_count": 0,
    "citation_count_without_self_citations": 0,
    "abs_url": "https://arxiv.org/abs/2607.15921v1",
    "pdf_url": "https://arxiv.org/pdf/2607.15921v1",
    "inspire_url": "https://inspirehep.net/literature/3181663",
    "is_update": false,
    "source_provenance": [
      {
        "source": "arxiv",
        "record_id": "2607.15921",
        "fetched_at": "2026-07-22T00:12:31.971466Z",
        "url": "https://arxiv.org/abs/2607.15921v1"
      },
      {
        "source": "inspire",
        "record_id": "3181663",
        "fetched_at": "2026-07-22T00:12:31.971466Z",
        "url": "https://inspirehep.net/literature/3181663"
      }
    ],
    "is_demo": false
  },
  "filter_result": {
    "schema_version": "1.0",
    "passed": false,
    "candidate_topics": [],
    "high_weight_hits": [],
    "medium_weight_hits": [],
    "negative_hits": [],
    "reasons": [
      "未达到主题关键词门槛"
    ],
    "deterministic_score": 0
  },
  "schema_version": "1.0"
}