{
  "paper": {
    "schema_version": "1.0",
    "canonical_key": "arxiv:2607.06738",
    "arxiv_id": "2607.06738",
    "arxiv_version": 1,
    "inspire_id": null,
    "doi": null,
    "title_en": "Integrable systems inspired by DAHA and DIM algebra: type $C^\\vee C$ versus type $A$",
    "abstract_en": "The Ding-Iohara-Miki (DIM) algebra (quantum toroidal algebra of $\\widehat{gl_1}$) is related to a wide class of quantum many-particle integrable systems, a typical one being the Ruijsenaars trigonometric system with eigenfunctions that are a triad formed by the Noumi-Shiraishi power series, the Macdonald polynomials, and the Baker-Akhiezer multivariable function. Other integrable systems of this type are obtained from the Ruijsenaars system by twisting. At the same time, the Ruijsenaars Hamiltonians are directly related to the Hamiltonians of another quantum integrable system, the Cherednik DAHA Hamiltonians of type $A$ (and their twisted versions in the twisted case), due to the correspondence between the DIM algebra and the spherical DAHA. The eigenfunctions of the DAHA Hamiltonians are non-symmetric Macdonald polynomials. Similarly, there is a class of integrable DAHA Hamiltonians of type $C^\\vee C$, the spherical version of which, in turn, allows one to generate integrable Koornwinder Hamiltonians. The eigenfunctions of these two integrable systems are, respectively, non-symmetric and symmetric Koornwinder polynomials, which are our main interest in this paper. Here we consider the cases of both type $A$ and type $C^\\vee C$ systems, since they are sufficiently similar, and point out important distinctions between them.",
    "authors": [
      "L. Bishler",
      "A. Mironov",
      "A. Popolitov"
    ],
    "categories": [
      "hep-th",
      "math-ph",
      "math.QA"
    ],
    "submitted_at": "2026-07-07T19:05:48Z",
    "updated_at": "2026-07-07T19:05:48Z",
    "document_types": [],
    "journal_ref": null,
    "publication_info": [],
    "citation_count": null,
    "citation_count_without_self_citations": null,
    "abs_url": "https://arxiv.org/abs/2607.06738v1",
    "pdf_url": "https://arxiv.org/pdf/2607.06738v1",
    "inspire_url": null,
    "is_update": false,
    "source_provenance": [
      {
        "source": "arxiv",
        "record_id": "2607.06738",
        "fetched_at": "2026-07-14T06:07:18.107481Z",
        "url": "https://arxiv.org/abs/2607.06738v1"
      }
    ],
    "is_demo": false
  },
  "filter_result": {
    "schema_version": "1.0",
    "passed": false,
    "candidate_topics": [],
    "high_weight_hits": [],
    "medium_weight_hits": [],
    "negative_hits": [],
    "reasons": [
      "未达到主题关键词门槛"
    ],
    "deterministic_score": 0
  },
  "schema_version": "1.0"
}