{
  "paper": {
    "schema_version": "1.0",
    "canonical_key": "arxiv:2607.12737",
    "arxiv_id": "2607.12737",
    "arxiv_version": 1,
    "inspire_id": null,
    "doi": null,
    "title_en": "Magnetic field-driven phase switching in the antiferromagnetic Mott insulator Ca$_3$(Ru$_{0.99}$Ti$_{0.01}$)$_2$O$_7$",
    "abstract_en": "A bandwidth-controlled antiferromagnetic Mott-insulating phase in Ca$_3$(Ru$_{1-x}$Ti$_x$)$_2$O$_7$ is realized through isovalent substitution at the Ru site. For a dilute substitution with only 1% Ti, the Mott insulator ground state remains nearly degenerate with the ground state of pristine Ca$_3$Ru$_2$O$_7$, where the Ru moments are ferromagnetically aligned within the metallic RuO$_2$ bilayers stacked in an antiferromagnetic fashion. The exceptionally shallow free energy landscape of this doped compound arises from intertwined electron-electron and electron-lattice interactions. This makes its magnetic and transport properties highly sensitive to external perturbations. We systematically investigated magnetic-field-induced phase switching in Ca$_3$(Ru$_{0.99}$Ti$_{0.01}$)$_2$O$_7$ to explore its magnetic $H$-$T$ phase diagram. With the field applied along the easy $b$-axis, parallel to the antiferromagnetic moments, the magnetization exhibits a first-order spin-flop transition at $\\approx $ 6 T, indicating reorientation of the Ru moments perpendicular to the field. The transition is accompanied by a decrease in the electrical resistance, but the spin-flop phase remains insulating. Above 10.5 T, all Ru moments align with the $b$-axis, resulting in a forced ferromagnetic metallic phase. In contrast, neither spin-flop nor forced-ferromagnetic phases are observed up to 14 T, when the field is applied along the $a$-axis. While the electronic kinetic energy and the electron-lattice coupling contribute to the free-energy balance of this system, the resulting $H$-$T$ phase diagram is remarkably simple and closely resembles that of a canonical anisotropic antiferromagnet, albeit with substantially renormalized critical fields.",
    "authors": [
      "Ksenia S. Rabinovich",
      "Tim Priessnitz",
      "Nils Gross",
      "George Jackeli",
      "Maximilian J. Krautloher",
      "Pascal Reiss",
      "Eberhard J. Goering",
      "Jurgen H. Smet",
      "Bernhard Keimer",
      "Alexander V. Boris"
    ],
    "categories": [
      "cond-mat.str-el"
    ],
    "submitted_at": "2026-07-14T13:09:26Z",
    "updated_at": "2026-07-14T13:09:26Z",
    "document_types": [],
    "journal_ref": null,
    "publication_info": [],
    "citation_count": null,
    "citation_count_without_self_citations": null,
    "abs_url": "https://arxiv.org/abs/2607.12737v1",
    "pdf_url": "https://arxiv.org/pdf/2607.12737v1",
    "inspire_url": null,
    "is_update": false,
    "source_provenance": [
      {
        "source": "arxiv",
        "record_id": "2607.12737",
        "fetched_at": "2026-07-20T00:17:04.949443Z",
        "url": "https://arxiv.org/abs/2607.12737v1"
      }
    ],
    "is_demo": false
  },
  "filter_result": {
    "schema_version": "1.0",
    "passed": false,
    "candidate_topics": [],
    "high_weight_hits": [],
    "medium_weight_hits": [],
    "negative_hits": [],
    "reasons": [
      "未达到主题关键词门槛"
    ],
    "deterministic_score": 0
  },
  "schema_version": "1.0"
}