{
  "paper": {
    "schema_version": "1.0",
    "canonical_key": "arxiv:2607.17346",
    "arxiv_id": "2607.17346",
    "arxiv_version": 1,
    "inspire_id": "3181888",
    "doi": null,
    "title_en": "The Information Content of Krylov Observables: A Machine Learning Approach",
    "abstract_en": "We employ machine learning to quantify the information carried by three Krylov-space observables: the spread complexity $\\mathcal{C}(t)$, the discrete Wigner negativity $N(t)$, and the normalized negativity $χ(t)=N(t)/|S(t)|$, with $S(t)$ the survival amplitude, recently proposed as a second-moment infall probe (arXiv:2607.04065). Small residual networks (16-32 neurons) and boosted trees are trained on half of $\\sim 57{,}000$ labeled evolutions spanning the GUE, GOE and Poisson ensembles, the integrable $SL(2,\\mathbb{R})$/CFT sector, and the chaos interpolation $H(\\varepsilon)=H_{SL(2,\\mathbb{R})}+\\varepsilon R_0 W_{GUE}$. Either moment determines the thermofield temperature at $R^2\\simeq 0.999$. Neither reconstructs the fine spectral form factor ($R^2\\simeq 0.18$ in every ensemble); smoothing the target does not repair this, and windows wide enough to help erase the dip-ramp physics itself: the SFF strictly refines both moments. The coarse $e^S$ plateau is nevertheless recovered at $R^2=0.861$, mostly from the first 20% of $\\mathcal{C}(t)$. A single curve identifies the symmetry class at up to 98% accuracy. In the integrable sector the observables are informationally equivalent, as exact negative-binomial slaving demands, while the negativity best resolves the $(h,α)$ degeneracy ($N\\to h$: 0.999). Along the interpolation the asymmetry gap of $χ$ over $\\mathcal{C}$ switches on with chaos, growing from +0.33 to +0.77 as the level statistics cross to GUE, while the raw-$N$ gap decays to zero. The second-moment informational surplus is therefore a signature of chaos, carried specifically by the normalized negativity, and we derive an analytical mechanism and a quantitative bound for it.",
    "authors": [
      "Ritam Basu"
    ],
    "categories": [
      "hep-th",
      "cond-mat.dis-nn",
      "cond-mat.stat-mech",
      "math-ph",
      "quant-ph"
    ],
    "submitted_at": "2026-07-19T00:00:00Z",
    "updated_at": "2026-07-21T11:54:35.249676Z",
    "document_types": [
      "article"
    ],
    "journal_ref": null,
    "publication_info": [],
    "citation_count": 0,
    "citation_count_without_self_citations": 0,
    "abs_url": "https://arxiv.org/abs/2607.17346v1",
    "pdf_url": "https://arxiv.org/pdf/2607.17346v1",
    "inspire_url": "https://inspirehep.net/literature/3181888",
    "is_update": false,
    "source_provenance": [
      {
        "source": "arxiv",
        "record_id": "2607.17346",
        "fetched_at": "2026-07-22T00:12:31.971466Z",
        "url": "https://arxiv.org/abs/2607.17346v1"
      },
      {
        "source": "inspire",
        "record_id": "3181888",
        "fetched_at": "2026-07-22T00:12:31.971466Z",
        "url": "https://inspirehep.net/literature/3181888"
      }
    ],
    "is_demo": false
  },
  "filter_result": {
    "schema_version": "1.0",
    "passed": false,
    "candidate_topics": [],
    "high_weight_hits": [],
    "medium_weight_hits": [],
    "negative_hits": [],
    "reasons": [
      "未达到主题关键词门槛"
    ],
    "deterministic_score": 0
  },
  "schema_version": "1.0"
}