{
  "paper": {
    "schema_version": "1.0",
    "canonical_key": "arxiv:2607.11468",
    "arxiv_id": "2607.11468",
    "arxiv_version": 1,
    "inspire_id": "3180005",
    "doi": null,
    "title_en": "Superconformal mechanics from N-extended Euler-Calogero-Moser and Calogero models",
    "abstract_en": "In this paper, we considered two-particle variants of the N-extended Euler-Calogero-Moser and Calogero models. Due the translation invariance, the center of mass can be decoupled (together with the corresponding fermions), leaving us with specific superconformal mechanics. Additional bosonic variables (spin variables) can easily be incorporated into the supercharges and the Hamiltonian. In the case of the Euler-Calogero-Moser model, the supersymmetry in the two-particle cases admits an unexpected extension from Osp(N|2) to SU(1,1|N) superconformal symmetry. The case of the Calogero model leads to purely Osp(N|2) superconformal mechanics. The way to get rid of the well-known problems along this path is to have a higher number of fermions present in the system.",
    "authors": [
      "S. Krivonos",
      "A. Sutulin"
    ],
    "categories": [
      "hep-th"
    ],
    "submitted_at": "2026-07-13T00:00:00Z",
    "updated_at": "2026-07-14T04:20:55.901188Z",
    "document_types": [
      "article"
    ],
    "journal_ref": null,
    "publication_info": [],
    "citation_count": 0,
    "citation_count_without_self_citations": 0,
    "abs_url": "https://arxiv.org/abs/2607.11468v1",
    "pdf_url": "https://arxiv.org/pdf/2607.11468v1",
    "inspire_url": "https://inspirehep.net/literature/3180005",
    "is_update": false,
    "source_provenance": [
      {
        "source": "arxiv",
        "record_id": "2607.11468",
        "fetched_at": "2026-07-14T05:21:02.416340Z",
        "url": "https://arxiv.org/abs/2607.11468v1"
      },
      {
        "source": "inspire",
        "record_id": "3180005",
        "fetched_at": "2026-07-14T05:21:02.416340Z",
        "url": "https://inspirehep.net/literature/3180005"
      }
    ],
    "is_demo": false
  },
  "filter_result": {
    "schema_version": "1.0",
    "passed": false,
    "candidate_topics": [],
    "high_weight_hits": [],
    "medium_weight_hits": [],
    "negative_hits": [],
    "reasons": [
      "未达到主题关键词门槛"
    ],
    "deterministic_score": 0
  },
  "schema_version": "1.0"
}