{
  "paper": {
    "schema_version": "1.0",
    "canonical_key": "arxiv:2607.19459",
    "arxiv_id": "2607.19459",
    "arxiv_version": 1,
    "inspire_id": "3182593",
    "doi": null,
    "title_en": "Strong Gravitational Lensing Posterior Sampling in Pixel-Space Using Diffusion Models and Recurrent Inference Machines",
    "abstract_en": "Modeling galaxy-galaxy strong gravitational lenses to infer the brightness of the source galaxy and the mass distribution of the foreground galaxy is computationally challenging, particularly for high-resolution, high signal-to-noise ratio observations. In this regime, high-dimensional representations of both the source and the foreground mass distribution are necessary to model the data down to the noise level. This inference problem has been challenging for both traditional and machine learning-based methods because of its high dimensionality and its non-linearity in the foreground mass distribution. We present a method to generate joint posterior samples of the source galaxy and foreground mass distribution as pixelated images conditioned on observations. The method combines diffusion-based generative modeling and recurrent inference machines. It can model realistic gravitational lensing simulations with background and foreground galaxies drawn from cosmological hydrodynamical simulations down to the noise level.",
    "authors": [
      "Guillaume Payeur",
      "Laurence Perreault-Levasseur",
      "Gabriel Missael Barco",
      "Yashar Hezaveh"
    ],
    "categories": [
      "astro-ph.IM",
      "astro-ph.CO",
      "cs.CV",
      "stat.ML"
    ],
    "submitted_at": "2026-07-21T00:00:00Z",
    "updated_at": "2026-07-23T04:25:53.498703Z",
    "document_types": [
      "conference paper"
    ],
    "journal_ref": null,
    "publication_info": [],
    "citation_count": 0,
    "citation_count_without_self_citations": 0,
    "abs_url": "https://arxiv.org/abs/2607.19459v1",
    "pdf_url": "https://arxiv.org/pdf/2607.19459v1",
    "inspire_url": "https://inspirehep.net/literature/3182593",
    "is_update": false,
    "source_provenance": [
      {
        "source": "arxiv",
        "record_id": "2607.19459",
        "fetched_at": "2026-07-24T00:15:37.724232Z",
        "url": "https://arxiv.org/abs/2607.19459v1"
      },
      {
        "source": "inspire",
        "record_id": "3182593",
        "fetched_at": "2026-07-24T00:15:37.724232Z",
        "url": "https://inspirehep.net/literature/3182593"
      }
    ],
    "is_demo": false
  },
  "filter_result": {
    "schema_version": "1.0",
    "passed": false,
    "candidate_topics": [],
    "high_weight_hits": [],
    "medium_weight_hits": [],
    "negative_hits": [],
    "reasons": [
      "未达到主题关键词门槛"
    ],
    "deterministic_score": 0
  },
  "schema_version": "1.0"
}