{
  "paper": {
    "schema_version": "1.0",
    "canonical_key": "arxiv:2504.04646",
    "arxiv_id": "2504.04646",
    "arxiv_version": 2,
    "inspire_id": null,
    "doi": "10.1088/1475-7516/2026/07/022",
    "title_en": "A New Window on Dynamical Dark Energy: Combining DESI-DR2 BAO with future Gravitational Wave Observations",
    "abstract_en": "Baryon acoustic oscillation (BAO) data from the Dark Energy Spectroscopic Instrument (DESI) appear to indicate the first evidence for dynamical dark energy (DDE), with a present-day behavior resembling quintessence. This evidence emerges when the Chevallier-Polarski-Linder (CPL) parameterization of the dark energy equation of state, $w_{\\textrm{de}} = w_0 + w_a (1-a)$, is considered, and persists across other functional forms of $w_{\\textrm{de}}$. In this work, we investigate how the inclusion of future gravitational wave (GW) standard siren data impacts the uncertainties in cosmological parameters when combined with DESI measurements. Specifically, we analyze the expected contributions from upcoming GW observatories such as the Einstein Telescope (ET) and the Deci-hertz Interferometer Gravitational-wave Observatory (DECIGO), as well as the current Laser Interferometer Gravitational-Wave Observatory (aLIGO). We find that the addition of GW data, particularly from DECIGO, significantly reduces the uncertainties in cosmological parameters, with the extent of the improvement depending on the specific form of $w_{\\textrm{de}}$ and being more expressive for the $Ω_m$ and $H_0$ parameters for all models studied. Our results highlight both the constraining power of future GW observations and the importance of considering a range of cosmological models in the data analysis.",
    "authors": [
      "Felipe Bruno Medeiros dos Santos",
      "Jonathan Morais",
      "Supriya Pan",
      "Weiqiang Yang",
      "Eleonora Di Valentino"
    ],
    "categories": [
      "astro-ph.CO"
    ],
    "submitted_at": "2025-04-07T00:03:58Z",
    "updated_at": "2026-07-08T17:43:17Z",
    "document_types": [],
    "journal_ref": null,
    "publication_info": [],
    "citation_count": null,
    "citation_count_without_self_citations": null,
    "abs_url": "https://arxiv.org/abs/2504.04646v2",
    "pdf_url": "https://arxiv.org/pdf/2504.04646v2",
    "inspire_url": null,
    "is_update": true,
    "source_provenance": [
      {
        "source": "arxiv",
        "record_id": "2504.04646",
        "fetched_at": "2026-07-13T12:53:32.407803Z",
        "url": "https://arxiv.org/abs/2504.04646v2"
      }
    ],
    "is_demo": false
  },
  "filter_result": {
    "schema_version": "1.0",
    "passed": false,
    "candidate_topics": [],
    "high_weight_hits": [],
    "medium_weight_hits": [],
    "negative_hits": [],
    "reasons": [
      "未达到主题关键词门槛"
    ],
    "deterministic_score": 0
  },
  "schema_version": "1.0"
}