{
  "paper": {
    "schema_version": "1.0",
    "canonical_key": "arxiv:2607.18071",
    "arxiv_id": "2607.18071",
    "arxiv_version": 1,
    "inspire_id": null,
    "doi": null,
    "title_en": "DFT+U+V is equivalent to DFT+U with density-dependent hybridized projectors",
    "abstract_en": "Hubbard-corrected density-functional theory (DFT+$U$) is a popular tool for first-principles modeling of materials with localized $d$ or $f$ electrons, but its on-site corrections tend to over-localize charge and break covalent bonds. Inter-site $+V$ corrections were introduced to counter this and are now widely used, but a formal justification has been lacking. Here we show that -- to first order in $V/U$ -- inter-site corrections are exactly equivalent to on-site DFT+$U$ evaluated on a density-dependent redefinition of the Hubbard projectors, hybridized with those of neighboring sites, providing insight into the explicit mechanism by which $V$ affects covalency. If the projectors are held frozen, as is common practice, the equivalence partially breaks down. Beyond reinterpreting the formalism, these results sharpen the questions of how $V$ should be computed and what the Hubbard subspaces fundamentally are.",
    "authors": [
      "Edward Linscott",
      "Alberto Carta",
      "Nicola Marzari"
    ],
    "categories": [
      "cond-mat.mtrl-sci",
      "cond-mat.str-el",
      "physics.chem-ph",
      "physics.comp-ph"
    ],
    "submitted_at": "2026-07-20T15:38:06Z",
    "updated_at": "2026-07-20T15:38:06Z",
    "document_types": [],
    "journal_ref": null,
    "publication_info": [],
    "citation_count": null,
    "citation_count_without_self_citations": null,
    "abs_url": "https://arxiv.org/abs/2607.18071v1",
    "pdf_url": "https://arxiv.org/pdf/2607.18071v1",
    "inspire_url": null,
    "is_update": false,
    "source_provenance": [
      {
        "source": "arxiv",
        "record_id": "2607.18071",
        "fetched_at": "2026-07-24T00:15:37.724232Z",
        "url": "https://arxiv.org/abs/2607.18071v1"
      }
    ],
    "is_demo": false
  },
  "filter_result": {
    "schema_version": "1.0",
    "passed": false,
    "candidate_topics": [],
    "high_weight_hits": [],
    "medium_weight_hits": [],
    "negative_hits": [],
    "reasons": [
      "未达到主题关键词门槛"
    ],
    "deterministic_score": 0
  },
  "schema_version": "1.0"
}