{
  "paper": {
    "schema_version": "1.0",
    "canonical_key": "arxiv:2601.19474",
    "arxiv_id": "2601.19474",
    "arxiv_version": 2,
    "inspire_id": null,
    "doi": "10.1103/6vfx-8kmm",
    "title_en": "The quasi-normal modes of relativistic Fokker-Planck kinetic theory",
    "abstract_en": "Employing the well-known unitary equivalence between Fokker-Planck operators and Schrödinger Hamiltonians, we compute the quasi-normal-mode spectrum of ultrarelativistic kinetic theories with momentum-space diffusion. We show that the collision operator reduces to a Dirac-delta Schrödinger problem in one spatial dimension, and to a Coulomb Schrödinger operator with hydrogenic spectrum in three dimensions. Finite spatial wavenumber appears as a perturbation of the associated quantum potential. The hydrodynamic mode is found to obey exact Fick-type diffusion at all real wavenumbers, whereas relativistic kinematics generically produces a continuous ballistic band in the non-hydrodynamic sector, a feature absent in the Newtonian regime.",
    "authors": [
      "Lorenzo Gavassino"
    ],
    "categories": [
      "nucl-th",
      "gr-qc",
      "hep-th",
      "math-ph"
    ],
    "submitted_at": "2026-01-27T11:05:15Z",
    "updated_at": "2026-07-08T14:44:23Z",
    "document_types": [],
    "journal_ref": "Phys. Rev. D 114, 014018 (8 July, 2026)",
    "publication_info": [],
    "citation_count": null,
    "citation_count_without_self_citations": null,
    "abs_url": "https://arxiv.org/abs/2601.19474v2",
    "pdf_url": "https://arxiv.org/pdf/2601.19474v2",
    "inspire_url": null,
    "is_update": true,
    "source_provenance": [
      {
        "source": "arxiv",
        "record_id": "2601.19474",
        "fetched_at": "2026-07-14T06:07:18.107481Z",
        "url": "https://arxiv.org/abs/2601.19474v2"
      }
    ],
    "is_demo": false
  },
  "filter_result": {
    "schema_version": "1.0",
    "passed": false,
    "candidate_topics": [],
    "high_weight_hits": [],
    "medium_weight_hits": [],
    "negative_hits": [],
    "reasons": [
      "未达到主题关键词门槛"
    ],
    "deterministic_score": 0
  },
  "schema_version": "1.0"
}