{
  "paper": {
    "schema_version": "1.0",
    "canonical_key": "arxiv:2607.19166",
    "arxiv_id": "2607.19166",
    "arxiv_version": 1,
    "inspire_id": "3182291",
    "doi": null,
    "title_en": "Boundary quenches in (1+1)-dimensional conformal field theory",
    "abstract_en": "We investigate a class of local quantum quenches in which the conformal boundary condition of a (1+1)-dimensional conformal field theory is abruptly changed. We derive a remarkably simple and universal expression for the time evolution of one-point functions on the half-line. This result provides a direct description of the propagation of the disturbance generated by the quench and, in turn, allows us to determine the dynamics of bipartite entanglement for subsystems adjacent to the boundary. We show that, once the subsystem becomes fully causally connected to the quench event, the entanglement entropy undergoes a sharp finite jump whose magnitude is universally given by the logarithm of the ratio of the boundary g-factors associated with the initial and final boundary conditions. We benchmark these analytical predictions against Matrix Product State simulations of the critical Ising spin chain, finding excellent agreement. The numerical analysis further allows us to investigate the time evolution of the spin-flip entanglement asymmetry, revealing how the symmetry-breaking perturbation emitted from the boundary propagates through the system. Our results uncover universal dynamical signatures of boundary quenches and establish a direct connection between nonequilibrium entanglement dynamics and boundary critical phenomena.",
    "authors": [
      "Michele Fossati",
      "Colin Rylands",
      "Eytan Grosfeld",
      "Eran Sela",
      "Pasquale Calabrese"
    ],
    "categories": [
      "cond-mat.stat-mech",
      "cond-mat.str-el",
      "hep-th",
      "quant-ph"
    ],
    "submitted_at": "2026-07-21T00:00:00Z",
    "updated_at": "2026-07-22T17:30:17.080165Z",
    "document_types": [
      "article"
    ],
    "journal_ref": null,
    "publication_info": [],
    "citation_count": 0,
    "citation_count_without_self_citations": 0,
    "abs_url": "https://arxiv.org/abs/2607.19166v1",
    "pdf_url": "https://arxiv.org/pdf/2607.19166v1",
    "inspire_url": "https://inspirehep.net/literature/3182291",
    "is_update": false,
    "source_provenance": [
      {
        "source": "arxiv",
        "record_id": "2607.19166",
        "fetched_at": "2026-07-23T00:16:56.820264Z",
        "url": "https://arxiv.org/abs/2607.19166v1"
      },
      {
        "source": "inspire",
        "record_id": "3182291",
        "fetched_at": "2026-07-23T00:16:56.820264Z",
        "url": "https://inspirehep.net/literature/3182291"
      }
    ],
    "is_demo": false
  },
  "filter_result": {
    "schema_version": "1.0",
    "passed": false,
    "candidate_topics": [],
    "high_weight_hits": [],
    "medium_weight_hits": [],
    "negative_hits": [],
    "reasons": [
      "未达到主题关键词门槛"
    ],
    "deterministic_score": 0
  },
  "schema_version": "1.0"
}