{
  "paper": {
    "schema_version": "1.0",
    "canonical_key": "arxiv:2607.12726",
    "arxiv_id": "2607.12726",
    "arxiv_version": null,
    "inspire_id": "3180425",
    "doi": null,
    "title_en": "Physically Consistent Parameter Inference: Transparent Machine Learning Emulation in High Energy Physics and Cosmology",
    "abstract_en": "Global fits in high energy physics and cosmology often face the challenge of exploring high-dimensional parameter spaces with computationally expensive or topologically complex likelihood functions. In this work, we present a Machine Learning framework designed to emulate complex, often non-Gaussian likelihood landscapes using gradient-boosted regression trees (XGBoost). We discuss the advantages of the Machine Learning approach in terms of computational efficiency and the resolution of confidence regions, particularly in scenarios with complex correlations or \"curved\" degeneracies. We validate this methodology by applying it to a recent analysis on flavour anomalies in semileptonic $B$ meson decays and discussing the adaptability of this framework to other phenomenological systems, such as axion-like particles or cosmology global fits. Finally, we utilise SHAP (Shapley Additive exPlanations) values to provide a transparent analysis of feature importance, ensuring that the Machine Learning predictions remain physically interpretable and consistent with the underlying physics.",
    "authors": [
      "Alda, Jorge",
      "Asorey, Jacobo",
      "Mir, Alejandro",
      "Peñaranda, Siannah"
    ],
    "categories": [],
    "submitted_at": "2026-07-14T00:00:00Z",
    "updated_at": "2026-07-16T04:11:29.292566Z",
    "document_types": [
      "article"
    ],
    "journal_ref": null,
    "publication_info": [],
    "citation_count": 0,
    "citation_count_without_self_citations": 0,
    "abs_url": null,
    "pdf_url": null,
    "inspire_url": "https://inspirehep.net/literature/3180425",
    "is_update": false,
    "source_provenance": [
      {
        "source": "inspire",
        "record_id": "3180425",
        "fetched_at": "2026-07-17T00:16:55.132478Z",
        "url": "https://inspirehep.net/literature/3180425"
      }
    ],
    "is_demo": false
  },
  "filter_result": {
    "schema_version": "1.0",
    "passed": false,
    "candidate_topics": [],
    "high_weight_hits": [],
    "medium_weight_hits": [],
    "negative_hits": [],
    "reasons": [
      "未达到主题关键词门槛"
    ],
    "deterministic_score": 0
  },
  "schema_version": "1.0"
}