{
  "paper": {
    "schema_version": "1.0",
    "canonical_key": "arxiv:2607.11546",
    "arxiv_id": "2607.11546",
    "arxiv_version": 1,
    "inspire_id": "3180240",
    "doi": "10.3847/1538-4357/ae7a31",
    "title_en": "Radio and X-ray flux rebrightening six years after outburst in a partially-obscured extreme changing-look AGN",
    "abstract_en": "SDSS J1548+2208 is a unique partially-obscured nuclear transient that exhibits multiwavelength outbursts in mid-infrared, X-ray and radio. We present the results from multiwavelength photometric and spectroscopic follow-up observations with a time span of ~2500 days since its discovery. We find that the mid-infrared and X-ray emission (with a hard X-ray spectrum) are still in a high flux level relative to the pre-flare state, suggesting a sudden increased, and possibly long-sustained accreting activity from central black hole. This is supported by the slowly-evolving high-ionization coronal lines. The mid-infrared color turns blue slowly in the rising phase, which is distinct from stellar tidal disruption events (TDEs). All these properties point to the origin of outbursts from an extreme changing-look AGN and the scenario with a normal TDE seems disfavored. The radio spectral energy distribution (SED) in ~0.65-15 GHz is unusual, displaying a double-peak feature with distinct variability characteristics. In addition, we find evidence for the late-time radio rebrightening more than six years since the initial outburst, as well as a possibly new X-ray flare, though the significance for the latter is not high. The peculiar radio flux and SED evolution could be explained by a nascent outflow expanding into and shocking circumnuclear diffuse medium filled by denser clouds. In this case, SDSS J1548+2208 represents a rare changing-look AGN which can launch radio outflows. Continued multiwavelength observations are required to map the dust and gas distribution on pc-scales, providing new insights into the environmental properties that could regulate AGN changing-look phenomenon.",
    "authors": [
      "Tianyao Zhou",
      "Xinwen Shu",
      "Lei Yang",
      "Tao Wu",
      "Luming Sun",
      "Yibo Wang",
      "Guobin Mou",
      "Ning Jiang",
      "Wenjie Zhang",
      "Hucheng Ding",
      "Fabao Zhang",
      "Yujun Yao",
      "Liming Dou",
      "Yogesh Chandola",
      "Ningyu Tang",
      "Jianguo Wang",
      "Tinggui Wang"
    ],
    "categories": [
      "astro-ph.HE",
      "astro-ph.GA"
    ],
    "submitted_at": "2026-07-13T00:00:00Z",
    "updated_at": "2026-07-14T04:37:03.398875Z",
    "document_types": [
      "article"
    ],
    "journal_ref": "ApJ, 1006, 6 (2026)",
    "publication_info": [
      "1006, ApJ, 1006, 6 (2026), 6, publication, 2026, 6, Astrophys.J."
    ],
    "citation_count": 0,
    "citation_count_without_self_citations": 0,
    "abs_url": "https://arxiv.org/abs/2607.11546v1",
    "pdf_url": "https://arxiv.org/pdf/2607.11546v1",
    "inspire_url": "https://inspirehep.net/literature/3180240",
    "is_update": false,
    "source_provenance": [
      {
        "source": "arxiv",
        "record_id": "2607.11546",
        "fetched_at": "2026-07-14T06:07:18.107481Z",
        "url": "https://arxiv.org/abs/2607.11546v1"
      },
      {
        "source": "inspire",
        "record_id": "3180240",
        "fetched_at": "2026-07-14T06:07:18.107481Z",
        "url": "https://inspirehep.net/literature/3180240"
      }
    ],
    "is_demo": false
  },
  "filter_result": {
    "schema_version": "1.0",
    "passed": false,
    "candidate_topics": [],
    "high_weight_hits": [],
    "medium_weight_hits": [],
    "negative_hits": [],
    "reasons": [
      "未达到主题关键词门槛"
    ],
    "deterministic_score": 0
  },
  "schema_version": "1.0"
}